onvif/__init__.py
onvif/onvif_client.py
onvif/wsdl/ver10/actionengine.wsdl
onvif/wsdl/ver10/analyticsdevice.wsdl
onvif/wsdl/ver10/deviceio.wsdl
onvif/wsdl/ver10/display.wsdl
onvif/wsdl/ver10/receiver.wsdl
onvif/wsdl/ver10/recording.wsdl
onvif/wsdl/ver10/replay.wsdl
onvif/wsdl/ver10/search.wsdl
onvif/wsdl/ver10/advancedsecurity/wsdl/advancedsecurity.wsdl
onvif/wsdl/ver10/credential/wsdl/credential.wsdl
onvif/wsdl/ver10/device/wsdl/devicemgmt.wsdl
onvif/wsdl/ver10/events/wsdl/event.wsdl
onvif/wsdl/ver10/media/wsdl/media.wsdl
onvif/wsdl/ver10/pacs/accesscontrol.wsdl
onvif/wsdl/ver10/pacs/accessrules.wsdl
onvif/wsdl/ver10/pacs/doorcontrol.wsdl
onvif/wsdl/ver10/pacs/types.xsd
onvif/wsdl/ver10/provisioning/wsdl/provisioning.wsdl
onvif/wsdl/ver10/schedule/wsdl/schedule.wsdl
onvif/wsdl/ver10/schema/common.xsd
onvif/wsdl/ver10/schema/metadatastream.xsd
onvif/wsdl/ver10/schema/onvif.xsd
onvif/wsdl/ver10/thermal/wsdl/thermal.wsdl
onvif/wsdl/ver20/analytics/radiometry.xsd
onvif/wsdl/ver20/analytics/rules.xsd
onvif/wsdl/ver20/analytics/wsdl/analytics.wsdl
onvif/wsdl/ver20/imaging/wsdl/imaging.wsdl
onvif/wsdl/ver20/media/wsdl/media.wsdl
onvif/wsdl/ver20/ptz/wsdl/ptz.wsdl
onvif_client-0.0.4.dist-info/LICENSE
onvif_client-0.0.4.dist-info/METADATA
onvif_client-0.0.4.dist-info/WHEEL
onvif_client-0.0.4.dist-info/top_level.txt
onvif_client-0.0.4.dist-info/RECORD
