Metadata-Version: 2.1
Name: onvif-client
Version: 0.0.4
Summary: onvif-client: WS-Discovery and Simple ONVIF camera client library
Home-page: https://github.com/hasimoka/onvif-client
Author: Katsuya Hashimoto
Maintainer: hasimoka@gmail.com
Maintainer-email: hasimoka@gmail.com
License: UNKNOWN
Download-URL: https://github.com/hasimoka/onvif-client
Platform: UNKNOWN
Classifier: Development Status :: 3 - Alpha
Classifier: Environment :: Console
Classifier: Intended Audience :: Developers
Classifier: Intended Audience :: Education
Classifier: License :: OSI Approved :: GNU Lesser General Public License v3 or later (LGPLv3+)
Classifier: Operating System :: MacOS :: MacOS X
Classifier: Operating System :: POSIX :: Linux
Classifier: Programming Language :: Python :: 3
Classifier: Programming Language :: Python :: 3.6
Classifier: Programming Language :: Python :: 3.7
Classifier: Programming Language :: Python :: 3.8
Classifier: Programming Language :: Python :: 3.9
Classifier: Programming Language :: Python :: 3 :: Only
Classifier: Topic :: Software Development :: Libraries
Classifier: Topic :: Software Development :: Libraries :: Python Modules
Classifier: Topic :: Communications
Requires-Python: >=3.9
License-File: LICENSE
Requires-Dist: WSDiscovery
Requires-Dist: onvif2-zeep
